plover_comment/__init__.py
plover_comment-0.0.2.dist-info/LICENSE
plover_comment-0.0.2.dist-info/METADATA
plover_comment-0.0.2.dist-info/WHEEL
plover_comment-0.0.2.dist-info/entry_points.txt
plover_comment-0.0.2.dist-info/top_level.txt
plover_comment-0.0.2.dist-info/zip-safe
plover_comment-0.0.2.dist-info/RECORD
