Metadata-Version: 2.1
Name: plover-comment
Version: 0.0.2
Summary: Plover plugin to add comment/meta-information to the outline definition.
Home-page: https://github.com/user202729/plover-comment
Author: user202729
License: GNU General Public License v3 or later (GPLv3+)
Keywords: plover plover_plugin
Classifier: Environment :: Plugins
Classifier: License :: OSI Approved :: GNU General Public License v3 or later (GPLv3+)
Classifier: Operating System :: OS Independent
Classifier: Programming Language :: Python :: 3
License-File: LICENSE
Requires-Dist: plover (>=4.0.0.dev8)
